{"assets/fonts/AvenirLTStd_Roman.otf":["assets/fonts/AvenirLTStd_Roman.otf"],"assets/fonts/BebasNeue_Regular.otf":["assets/fonts/BebasNeue_Regular.otf"],"assets/images/demo_coffee_1.jpeg":["assets/images/demo_coffee_1.jpeg"],"assets/images/demo_coffee_1.png":["assets/images/demo_coffee_1.png"],"assets/images/logo_kopi_nu.png":["assets/images/logo_kopi_nu.png"],"assets/images/pic_artisan.png":["assets/images/pic_artisan.png"],"assets/images/pic_farhan.png":["assets/images/pic_farhan.png"],"assets/images/pic_galih.png":["assets/images/pic_galih.png"],"assets/images/pic_manual.png":["assets/images/pic_manual.png"],"assets/images/slide_1.jpeg":["assets/images/slide_1.jpeg"],"assets/images/slide_2.jpeg":["assets/images/slide_2.jpeg"],"assets/images/slide_3.jpeg":["assets/images/slide_3.jpeg"],"assets/images/speciality_detail.png":["assets/images/speciality_detail.png"],"packages/cupertino_icons/assets/CupertinoIcons.ttf":["packages/cupertino_icons/assets/CupertinoIcons.ttf"]}